kai_client/__init__.py
kai_client/cli.py
kai_client/client.py
kai_client/exceptions.py
kai_client/models.py
kai_client/py.typed
kai_client/sse.py
kai_client/types.py
kai_client-0.8.0.dist-info/METADATA
kai_client-0.8.0.dist-info/WHEEL
kai_client-0.8.0.dist-info/entry_points.txt
kai_client-0.8.0.dist-info/licenses/LICENSE
kai_client-0.8.0.dist-info/RECORD
