Metadata-Version: 2.4
Name: kai-client
Version: 0.8.0
Summary: Python client library for the Keboola AI Assistant Backend API
Project-URL: Homepage, https://github.com/keboola/kai-client
Project-URL: Documentation, https://github.com/keboola/kai-client#readme
Project-URL: Repository, https://github.com/keboola/kai-client
Author-email: Keboola <support@keboola.com>
License: MIT
License-File: LICENSE
Keywords: ai,api,assistant,client,keboola,sse,streaming
Classifier: Development Status :: 4 - Beta
Classifier: Intended Audience :: Developers
Classifier: License :: OSI Approved :: MIT License
Classifier: Programming Language :: Python :: 3
Classifier: Programming Language :: Python :: 3.10
Classifier: Programming Language :: Python :: 3.11
Classifier: Programming Language :: Python :: 3.12
Classifier: Typing :: Typed
Requires-Python: >=3.10
Requires-Dist: click>=8.0
Requires-Dist: httpx>=0.27.0
Requires-Dist: pydantic>=2.0
Requires-Dist: python-dotenv>=1.0.0
Provides-Extra: dev
Requires-Dist: pytest-asyncio>=0.24.0; extra == 'dev'
Requires-Dist: pytest-httpx>=0.32.0; extra == 'dev'
Requires-Dist: pytest>=8.0; extra == 'dev'
